{
  "schemaVersion": 1,
  "id": "chas",
  "version": "3.0",
  "name": "Craftable Horse Armor & Saddle",
  "description": "Makes horse armor and saddles craftable",
  "authors": [
    "Ewy"
  ],
  "contact": {
    "homepage": "https://github.com/EwyBoy/CHA-S",
    "sources": "https://github.com/EwyBoy/CHA-S",
    "issues": "https://github.com/EwyBoy/CHA-S/issues"
  },
  "license": "MIT",
  "environment": "*",
  "entrypoints": {
    "main": [
      "com.ewyboy.chas.fabric.CraftableHorseArmourFabric"
    ]
  },
  "depends": {
    "fabricloader": ">=0.15.11",
    "fabric-api": "*",
    "minecraft": "1.21",
    "java": ">=21"
  }
}